[
  {
    "secCode": "5987",
    "filerName": "株式会社オーネックス",
    "docID": "S100UG24",
    "docPdfURL": "https://disclosure2dl.edinet-fsa.go.jp/searchdocument/pdf/S100UG24.pdf",
    "yahooURL": "https://finance.yahoo.co.jp/quote/5987.T",
    "periodEnd": "2024年6月期",
    "characteristic": "(セグメント情報等)【セグメント情報】１．報告セグメントの概要当社グループの報告セグメントは、当社グループの構成単位のうち分離された財務情報が入手可能であり、取締役会が、経営資源の配分の決定及び業績を評価するために、定期的に検討を行う対象となっているものであります。",
    "stockPrice": null,
    "netSales": 4967499000.0,
    "employees": 247,
    "operatingIncome": 55975000.0,
    "operatingIncomeRate": 1.1268245851685124,
    "depreciation": 527535000.0,
    "ebitda": 583510000.0,
    "ebitdaMargin": 11.746554956528426,
    "marketCapitalization": null,
    "per": 5.0,
    "ev": null,
    "evPerEbitda": null,
    "pbr": null,
    "bps": 3186.61,
    "equity": 5276190000.0,
    "debt": 1417651000.0,
    "outstandingShares": 1650500,
    "netIncome": -377470000.0,
    "eps": -227.97,
    "cash": 2707562000.0,
    "retrievedDate": "2025-06-29"
  },
  {
    "secCode": "6340",
    "filerName": "澁谷工業株式会社",
    "docID": "S100UFKR",
    "docPdfURL": "https://disclosure2dl.edinet-fsa.go.jp/searchdocument/pdf/S100UFKR.pdf",
    "yahooURL": "https://finance.yahoo.co.jp/quote/6340.T",
    "periodEnd": "2024年6月期",
    "characteristic": "（企業結合等関係） 取得による企業結合 １．企業結合の概要 (1）被取得企業の名称および事業の内容 被取得企業の名称 綜和機電㈱ 事業の内容 半導体製造、検査装置の設計製作および販売 (2）企業結合を行った主な理由 綜和機電㈱ではＩＣパッケージを検査するテストハンドラ、ＩＣパッケージにレーザマークするレーザマークハンドラを製造販売しており、近年は特にパワー半導体関連装置を主体に事業展開しております。",
    "stockPrice": 3570.754,
    "netSales": 115434000000.0,
    "employees": 3248,
    "operatingIncome": 13382000000.0,
    "operatingIncomeRate": 11.592771627076944,
    "depreciation": 2935000000.0,
    "ebitda": 16317000000.0,
    "ebitdaMargin": 14.135350070169967,
    "marketCapitalization": 98708852349.8,
    "per": 10.1,
    "ev": 55510852349.8,
    "evPerEbitda": 3.402025638891953,
    "pbr": 0.9779190333517738,
    "bps": 3651.38,
    "equity": 101029000000.0,
    "debt": 3696000000.0,
    "outstandingShares": 27643700,
    "netIncome": 9781000000.0,
    "eps": 353.54,
    "cash": 46894000000.0,
    "retrievedDate": "2025-06-29"
  },
  {
    "secCode": "7500",
    "filerName": "西川計測株式会社",
    "docID": "S100UFT7",
    "docPdfURL": "https://disclosure2dl.edinet-fsa.go.jp/searchdocument/pdf/S100UFT7.pdf",
    "yahooURL": "https://finance.yahoo.co.jp/quote/7500.T",
    "periodEnd": "2024年6月期",
    "characteristic": "社内ITインフラ環境の整備および強化を目的としたサービス提供を受けることで今後の事業発展における安定的なシステム環境を確保するため(株式数が増加した理由)上記保有目的による新規株式の取得",
    "stockPrice": null,
    "netSales": null,
    "employees": null,
    "operatingIncome": null,
    "operatingIncomeRate": null,
    "depreciation": null,
    "ebitda": null,
    "ebitdaMargin": null,
    "marketCapitalization": null,
    "per": 50.0,
    "ev": null,
    "evPerEbitda": null,
    "pbr": null,
    "bps": 937.3940558923555,
    "equity": 3169798000.0,
    "debt": null,
    "outstandingShares": 3381500,
    "netIncome": null,
    "eps": null,
    "cash": null,
    "retrievedDate": "2025-06-29"
  },
  {
    "secCode": "1764",
    "filerName": "工藤建設株式会社",
    "docID": "S100UGBY",
    "docPdfURL": "https://disclosure2dl.edinet-fsa.go.jp/searchdocument/pdf/S100UGBY.pdf",
    "yahooURL": "https://finance.yahoo.co.jp/quote/1764.T",
    "periodEnd": "2024年6月期",
    "characteristic": "３ 【事業の内容】当社グループは、当社及び関連会社２社で構成され、建設工事・土木工事の請負、不動産の売買・賃貸、建物総合管理事業及び高齢者向け介護事業を主な事業とし、さらに各事業に関連する事業を行っております。",
    "stockPrice": null,
    "netSales": null,
    "employees": null,
    "operatingIncome": null,
    "operatingIncomeRate": null,
    "depreciation": null,
    "ebitda": null,
    "ebitdaMargin": null,
    "marketCapitalization": null,
    "per": 30.0,
    "ev": null,
    "evPerEbitda": null,
    "pbr": null,
    "bps": 200.83185268938783,
    "equity": 248670000.0,
    "debt": null,
    "outstandingShares": 1238200,
    "netIncome": null,
    "eps": null,
    "cash": null,
    "retrievedDate": "2025-06-29"
  },
  {
    "secCode": "3446",
    "filerName": "株式会社ジェイテックコーポレーション",
    "docID": "S100UGCE",
    "docPdfURL": "https://disclosure2dl.edinet-fsa.go.jp/searchdocument/pdf/S100UGCE.pdf",
    "yahooURL": "https://finance.yahoo.co.jp/quote/3446.T",
    "periodEnd": "2024年6月期",
    "characteristic": "３【事業の内容】 当社グループ（当社及び当社の関係会社）は、当社（株式会社ジェイテックコーポレーション）、及び子会社１社（電子科学株式会社）により構成しております。",
    "stockPrice": 1610.7228,
    "netSales": 2010340000.0,
    "employees": 64,
    "operatingIncome": 285836000.0,
    "operatingIncomeRate": 14.218291433289892,
    "depreciation": 106771000.0,
    "ebitda": 392607000.0,
    "ebitdaMargin": 19.52938308942766,
    "marketCapitalization": 9455426052.84,
    "per": 47.43,
    "ev": 9291703052.84,
    "evPerEbitda": 23.666676989559534,
    "pbr": 3.5114185433062284,
    "bps": 458.71,
    "equity": 2696776000.0,
    "debt": 446507000.0,
    "outstandingShares": 5870300,
    "netIncome": 199591000.0,
    "eps": 33.96,
    "cash": 610230000.0,
    "retrievedDate": "2025-06-29"
  },
  {
    "secCode": "1431",
    "filerName": "株式会社Ｌｉｂ　Ｗｏｒｋ",
    "docID": "S100UGCI",
    "docPdfURL": "https://disclosure2dl.edinet-fsa.go.jp/searchdocument/pdf/S100UGCI.pdf",
    "yahooURL": "https://finance.yahoo.co.jp/quote/1431.T",
    "periodEnd": "2024年6月期",
    "characteristic": "(企業結合等関係) 取得による企業結合 (1)企業結合の概要 ①被取得企業の名称及びその事業内容 被取得企業の名称 幸の国木材工業株式会社 事業の内容 製材加工販売等 ②企業結合を行った主な理由当社グループは、「デジタルマーケティングをコアコンピタンスとするHouse Tech Company」として、「サステナブル＆テクノロジーで住まいにイノベーションを起こす」というミッションを掲げております。",
    "stockPrice": 709.464,
    "netSales": 15435172000.0,
    "employees": 308,
    "operatingIncome": 495802000.0,
    "operatingIncomeRate": 3.2121572730125716,
    "depreciation": 229653000.0,
    "ebitda": 725455000.0,
    "ebitdaMargin": 4.700012413207964,
    "marketCapitalization": 16912557564.000002,
    "per": 41.2,
    "ev": 14513478564.0,
    "evPerEbitda": 20.00603561075463,
    "pbr": 3.6532646755921734,
    "bps": 194.2,
    "equity": 4570600000.0,
    "debt": 1379309000.0,
    "outstandingShares": 23838500,
    "netIncome": 387574000.0,
    "eps": 17.22,
    "cash": 3778388000.0,
    "retrievedDate": "2025-06-29"
  },
  {
    "secCode": "7377",
    "filerName": "ＤＮホールディングス株式会社",
    "docID": "S100UE7Z",
    "docPdfURL": "https://disclosure2dl.edinet-fsa.go.jp/searchdocument/pdf/S100UE7Z.pdf",
    "yahooURL": "https://finance.yahoo.co.jp/quote/7377.T",
    "periodEnd": "2024年6月期",
    "characteristic": "(企業結合等関係)取得による企業結合 当社の連結子会社である大日本ダイヤコンサルタント株式会社は、2024年２月20日開催の取締役会において、株式会社ウエルアップの全株式を取得し、子会社化することについて決議し、同日付で株式譲渡契約を締結いたしました。",
    "stockPrice": 1620.1616999999999,
    "netSales": 34131911000.0,
    "employees": 1453,
    "operatingIncome": 1948233000.0,
    "operatingIncomeRate": 5.7079517170896175,
    "depreciation": 396887000.0,
    "ebitda": 2345120000.0,
    "ebitdaMargin": 6.870755053826315,
    "marketCapitalization": 13104839926.619999,
    "per": 8.43,
    "ev": 11687944926.619999,
    "evPerEbitda": 4.983943221080371,
    "pbr": 0.9739358108108107,
    "bps": 1663.52,
    "equity": 13486462000.0,
    "debt": 700000000.0,
    "outstandingShares": 8088600,
    "netIncome": 1557407000.0,
    "eps": 192.19,
    "cash": 2116895000.0,
    "retrievedDate": "2025-06-29"
  },
  {
    "secCode": "1788",
    "filerName": "株式会社三東工業社",
    "docID": "S100UG22",
    "docPdfURL": "https://disclosure2dl.edinet-fsa.go.jp/searchdocument/pdf/S100UG22.pdf",
    "yahooURL": "https://finance.yahoo.co.jp/quote/1788.T",
    "periodEnd": "2024年6月期",
    "characteristic": "３【事業の内容】 当社グループ（当社及び当社の関係会社）は、当社及び子会社２社により構成されております。",
    "stockPrice": 3580.9809999999998,
    "netSales": 7400143000.0,
    "employees": 117,
    "operatingIncome": 199295000.0,
    "operatingIncomeRate": 2.6931236328811483,
    "depreciation": 60317000.0,
    "ebitda": 259612000.0,
    "ebitdaMargin": 3.508202476627816,
    "marketCapitalization": 243148609.89999998,
    "per": 16.7,
    "ev": -551682390.1,
    "evPerEbitda": -2.1250265399904475,
    "pbr": 0.6976661860972568,
    "bps": 5132.8,
    "equity": 3209891000.0,
    "debt": 500000000.0,
    "outstandingShares": 67900,
    "netIncome": 132314000.0,
    "eps": 214.43,
    "cash": 1294831000.0,
    "retrievedDate": "2025-06-29"
  },
  {
    "secCode": "9344",
    "filerName": "アクシスコンサルティング株式会社",
    "docID": "S100UGF4",
    "docPdfURL": "https://disclosure2dl.edinet-fsa.go.jp/searchdocument/pdf/S100UGF4.pdf",
    "yahooURL": "https://finance.yahoo.co.jp/quote/9344.T",
    "periodEnd": "2024年6月期",
    "characteristic": "３【事業の内容】 (1）理念・ビジョン 当社は、「人が活きる、人を活かす。",
    "stockPrice": 1032.8802,
    "netSales": 4665926000.0,
    "employees": 117,
    "operatingIncome": 833755000.0,
    "operatingIncomeRate": 17.86901463932347,
    "depreciation": 34898000.0,
    "ebitda": 868653000.0,
    "ebitdaMargin": 18.61694763268856,
    "marketCapitalization": 5153968909.9800005,
    "per": 10.41,
    "ev": 2131535909.9800005,
    "evPerEbitda": 2.4538404978512713,
    "pbr": 1.6275826097918407,
    "bps": 634.61,
    "equity": 3168324000.0,
    "debt": 940000.0,
    "outstandingShares": 4989900,
    "netIncome": 502669000.0,
    "eps": 99.22,
    "cash": 3023373000.0,
    "retrievedDate": "2025-06-29"
  },
  {
    "secCode": "4068",
    "filerName": "ベイシス株式会社",
    "docID": "S100UGGR",
    "docPdfURL": "https://disclosure2dl.edinet-fsa.go.jp/searchdocument/pdf/S100UGGR.pdf",
    "yahooURL": "https://finance.yahoo.co.jp/quote/4068.T",
    "periodEnd": "2024年6月期",
    "characteristic": "（企業結合等関係） （取得による企業結合） １．企業結合の概要 (1) 被取得企業の名称及びその事業の内容 被取得企業の名称 株式会社アヴァンセ・アジル 事業の内容 人材派遣業 (2) 企業結合を行った主な理由 当社は、「ICT で世の中をもっと便利に」という経営理念の下、超スマート社会の実現に必要なモバイ ル（５G、６G）・IoT・IT 等のインフラを創り支えることで、世の中をより便利にすることを目指しております。",
    "stockPrice": 1201.5810000000001,
    "netSales": 6822403000.0,
    "employees": 568,
    "operatingIncome": 79274000.0,
    "operatingIncomeRate": 1.1619659524657222,
    "depreciation": 37203000.0,
    "ebitda": 116477000.0,
    "ebitdaMargin": 1.7072723496398556,
    "marketCapitalization": 2232177023.7000003,
    "per": 171.9,
    "ev": 1505070023.7000003,
    "evPerEbitda": 12.92160704430918,
    "pbr": 1.1361071452209184,
    "bps": 1057.63,
    "equity": 1966852000.0,
    "debt": 243750000.0,
    "outstandingShares": 1857700,
    "netIncome": 13158000.0,
    "eps": 6.99,
    "cash": 970857000.0,
    "retrievedDate": "2025-06-29"
  },
  {
    "secCode": "3597",
    "filerName": "株式会社自重堂",
    "docID": "S100UGAF",
    "docPdfURL": "https://disclosure2dl.edinet-fsa.go.jp/searchdocument/pdf/S100UGAF.pdf",
    "yahooURL": "https://finance.yahoo.co.jp/quote/3597.T",
    "periodEnd": "2024年6月期",
    "characteristic": "３【事業の内容】 当社グループ（当社及び当社の関係会社）は、株式会社自重堂（当社）、子会社２社及び関連会社２社により構成されており、ユニフォーム及びメンズウェアの企画、製造、販売を主な内容とした事業活動を行っております。",
    "stockPrice": 11049.572,
    "netSales": 16863582000.0,
    "employees": 185,
    "operatingIncome": 2610441000.0,
    "operatingIncomeRate": 15.479753945514066,
    "depreciation": 158182000.0,
    "ebitda": 2768623000.0,
    "ebitdaMargin": 16.41776343839642,
    "marketCapitalization": 31313382090.8,
    "per": 15.8,
    "ev": null,
    "evPerEbitda": null,
    "pbr": 0.8309985755907088,
    "bps": 13296.74,
    "equity": 38326072000.0,
    "debt": null,
    "outstandingShares": 2833900,
    "netIncome": 2015867000.0,
    "eps": 699.34,
    "cash": 11012240000.0,
    "retrievedDate": "2025-06-29"
  },
  {
    "secCode": "9159",
    "filerName": "株式会社Ｗ　ＴＯＫＹＯ",
    "docID": "S100UGHM",
    "docPdfURL": "https://disclosure2dl.edinet-fsa.go.jp/searchdocument/pdf/S100UGHM.pdf",
    "yahooURL": "https://finance.yahoo.co.jp/quote/9159.T",
    "periodEnd": "2024年6月期",
    "characteristic": "３【事業の内容】 当社グループ（当社及び当社の関係会社）は、当社、非連結子会社㈱W labで構成されております。",
    "stockPrice": null,
    "netSales": null,
    "employees": null,
    "operatingIncome": null,
    "operatingIncomeRate": null,
    "depreciation": null,
    "ebitda": null,
    "ebitdaMargin": null,
    "marketCapitalization": null,
    "per": 0.0277,
    "ev": null,
    "evPerEbitda": null,
    "pbr": null,
    "bps": null,
    "equity": null,
    "debt": null,
    "outstandingShares": 2705900,
    "netIncome": null,
    "eps": null,
    "cash": null,
    "retrievedDate": "2025-06-29"
  },
  {
    "secCode": "1716",
    "filerName": "第一カッター興業株式会社",
    "docID": "S100UG8N",
    "docPdfURL": "https://disclosure2dl.edinet-fsa.go.jp/searchdocument/pdf/S100UG8N.pdf",
    "yahooURL": "https://finance.yahoo.co.jp/quote/1716.T",
    "periodEnd": "2024年6月期",
    "characteristic": "３【事業の内容】 当社グループは、当社（第一カッター興業株式会社）、連結子会社４社（株式会社ウォールカッティング工業、株式会社新伸興業、株式会社アシレ、株式会社ユニペック）、持分法適用関連会社２社（ダイヤモンド機工株式会社、株式会社ムーバブルトレードネットワークス）で構成されており、切断・穿孔工事事業、ビルメンテナンス事業及びリユース・リサイクル事業を展開しております。",
    "stockPrice": 1604.2959999999998,
    "netSales": 20918336000.0,
    "employees": 629,
    "operatingIncome": 2455559000.0,
    "operatingIncomeRate": 11.738787444660991,
    "depreciation": 735064000.0,
    "ebitda": 3190623000.0,
    "ebitdaMargin": 15.252757198278106,
    "marketCapitalization": 18423895693.6,
    "per": 9.2,
    "ev": 9152198693.599998,
    "evPerEbitda": 2.868467598208876,
    "pbr": 0.9982925129430504,
    "bps": 1607.04,
    "equity": 18285321000.0,
    "debt": 191807000.0,
    "outstandingShares": 11484100,
    "netIncome": 1973240000.0,
    "eps": 174.38,
    "cash": 9463504000.0,
    "retrievedDate": "2025-06-29"
  },
  {
    "secCode": "3271",
    "filerName": "株式会社　ＴＨＥグローバル社",
    "docID": "S100UGI5",
    "docPdfURL": "https://disclosure2dl.edinet-fsa.go.jp/searchdocument/pdf/S100UGI5.pdf",
    "yahooURL": "https://finance.yahoo.co.jp/quote/3271.T",
    "periodEnd": "2024年6月期",
    "characteristic": "３【事業の内容】 当社グループは、2023年10月１日、当社を存続会社、当社完全子会社である株式会社グローバル・エルシード及び株式会社グローバル・キャストを消滅会社とする吸収合併をいたしました。",
    "stockPrice": 487.2228,
    "netSales": 27037074000.0,
    "employees": 143,
    "operatingIncome": 1757869000.0,
    "operatingIncomeRate": 6.501698371650718,
    "depreciation": 29233000.0,
    "ebitda": 1787102000.0,
    "ebitdaMargin": 6.609820278629262,
    "marketCapitalization": 13788453962.28,
    "per": 5.08,
    "ev": 10157457962.28,
    "evPerEbitda": 5.683759495697504,
    "pbr": 1.7332104869979723,
    "bps": 281.11,
    "equity": 7957202000.0,
    "debt": 807383000.0,
    "outstandingShares": 28300100,
    "netIncome": 2714925000.0,
    "eps": 95.91,
    "cash": 4438379000.0,
    "retrievedDate": "2025-06-29"
  },
  {
    "secCode": "5994",
    "filerName": "株式会社ファインシンター",
    "docID": "S100UGJZ",
    "docPdfURL": "https://disclosure2dl.edinet-fsa.go.jp/searchdocument/pdf/S100UGJZ.pdf",
    "yahooURL": "https://finance.yahoo.co.jp/quote/5994.T",
    "periodEnd": "2024年3月期",
    "characteristic": "自動車焼結事業の主要な取引先であり、安定的な取引の維持と営業取引関係の強化を目的に保有しております。",
    "stockPrice": null,
    "netSales": 42390968000.0,
    "employees": 2098,
    "operatingIncome": 413224000.0,
    "operatingIncomeRate": 0.9747925548668764,
    "depreciation": 3304402000.0,
    "ebitda": 3717626000.0,
    "ebitdaMargin": 8.769853993426146,
    "marketCapitalization": null,
    "per": 7.0,
    "ev": null,
    "evPerEbitda": null,
    "pbr": null,
    "bps": 3689.89,
    "equity": 18505357000.0,
    "debt": 4788272000.0,
    "outstandingShares": 4227200,
    "netIncome": -593463000.0,
    "eps": -135.62,
    "cash": 3865107000.0,
    "retrievedDate": "2025-06-29"
  },
  {
    "secCode": "4052",
    "filerName": "フィーチャ株式会社",
    "docID": "S100UGKF",
    "docPdfURL": "https://disclosure2dl.edinet-fsa.go.jp/searchdocument/pdf/S100UGKF.pdf",
    "yahooURL": "https://finance.yahoo.co.jp/quote/4052.T",
    "periodEnd": "2024年6月期",
    "characteristic": "３【事業の内容】 当社グループは、当社（フィーチャ株式会社）及び連結子会社である北京飞澈科技有限公司により構成されており、「Make Things Intelligent」をミッションとして掲げ、画像認識ソフトウェア開発事業を行っております。",
    "stockPrice": null,
    "netSales": 494209000.0,
    "employees": 32,
    "operatingIncome": -3567000.0,
    "operatingIncomeRate": -0.721759417574346,
    "depreciation": 12859000.0,
    "ebitda": 9292000.0,
    "ebitdaMargin": 1.8801762007571696,
    "marketCapitalization": null,
    "per": 124.76,
    "ev": null,
    "evPerEbitda": null,
    "pbr": null,
    "bps": 124.76,
    "equity": 729879000.0,
    "debt": null,
    "outstandingShares": 5846700,
    "netIncome": -7884000.0,
    "eps": -1.35,
    "cash": 578443000.0,
    "retrievedDate": "2025-06-29"
  },
  {
    "secCode": "5125",
    "filerName": "株式会社ファインズ",
    "docID": "S100UGFD",
    "docPdfURL": "https://disclosure2dl.edinet-fsa.go.jp/searchdocument/pdf/S100UGFD.pdf",
    "yahooURL": "https://finance.yahoo.co.jp/quote/5125.T",
    "periodEnd": "2024年6月期",
    "characteristic": "３【事業の内容】 当社は、「誰からも必要とされる会社になる」という経営理念のもと、事業を通じてすべてのステークホルダーのみなさまから必要とされる会社を目指しております。",
    "stockPrice": null,
    "netSales": null,
    "employees": null,
    "operatingIncome": null,
    "operatingIncomeRate": null,
    "depreciation": null,
    "ebitda": null,
    "ebitdaMargin": null,
    "marketCapitalization": null,
    "per": 0.0005,
    "ev": null,
    "evPerEbitda": null,
    "pbr": null,
    "bps": null,
    "equity": null,
    "debt": null,
    "outstandingShares": 4625300,
    "netIncome": null,
    "eps": null,
    "cash": null,
    "retrievedDate": "2025-06-29"
  },
  {
    "secCode": "9219",
    "filerName": "株式会社ギックス",
    "docID": "S100UGGG",
    "docPdfURL": "https://disclosure2dl.edinet-fsa.go.jp/searchdocument/pdf/S100UGGG.pdf",
    "yahooURL": "https://finance.yahoo.co.jp/quote/9219.T",
    "periodEnd": "2024年6月期",
    "characteristic": "３【事業の内容】 当社グループは、戦略コンサルティングの“データを用いて考える”という思考法と“データを考える材料に昇華する”高度なアナリティクス能力を組み合わせた、新しいタイプのプロフェッショナルサービス集団です。",
    "stockPrice": 1159.5658,
    "netSales": 2117723000.0,
    "employees": 73,
    "operatingIncome": 133830000.0,
    "operatingIncomeRate": 6.319523374870084,
    "depreciation": null,
    "ebitda": null,
    "ebitdaMargin": null,
    "marketCapitalization": 6469217598.200001,
    "per": 73.67,
    "ev": 4742685598.200001,
    "evPerEbitda": null,
    "pbr": 3.2699749020050195,
    "bps": 354.61,
    "equity": 2011822000.0,
    "debt": 45817000.0,
    "outstandingShares": 5579000,
    "netIncome": 88195000.0,
    "eps": 15.74,
    "cash": 1772349000.0,
    "retrievedDate": "2025-06-29"
  },
  {
    "secCode": "6031",
    "filerName": "サイジニア株式会社",
    "docID": "S100UG6Z",
    "docPdfURL": "https://disclosure2dl.edinet-fsa.go.jp/searchdocument/pdf/S100UG6Z.pdf",
    "yahooURL": "https://finance.yahoo.co.jp/quote/6031.T",
    "periodEnd": "2024年6月期",
    "characteristic": "３ 【事業の内容】当社グループは、当社及び連結子会社３社で構成され、「パーソナライズ」という切り口で、人工知能技術及びビッグデータ解析技術を活用し、顧客におけるマーケティング活動を支援する事業（以下「デジタルマーケティングソリューション事業」という。",
    "stockPrice": 476.28,
    "netSales": 1739748000.0,
    "employees": 71,
    "operatingIncome": 498583000.0,
    "operatingIncomeRate": 28.658345921363328,
    "depreciation": 21991000.0,
    "ebitda": 520574000.0,
    "ebitdaMargin": 29.92237956301717,
    "marketCapitalization": 4927021344.0,
    "per": 31.5,
    "ev": 3883482344.0,
    "evPerEbitda": 7.46000058397077,
    "pbr": 8.797192463982267,
    "bps": 54.14,
    "equity": 1120339000.0,
    "debt": 100846000.0,
    "outstandingShares": 10344800,
    "netIncome": 312357000.0,
    "eps": 15.12,
    "cash": 1144385000.0,
    "retrievedDate": "2025-06-29"
  },
  {
    "secCode": "7369",
    "filerName": "株式会社メイホーホールディングス",
    "docID": "S100UGIO",
    "docPdfURL": "https://disclosure2dl.edinet-fsa.go.jp/searchdocument/pdf/S100UGIO.pdf",
    "yahooURL": "https://finance.yahoo.co.jp/quote/7369.T",
    "periodEnd": "2024年6月期",
    "characteristic": "（企業結合等関係） 取得による企業結合 １．株式会社フジ土木設計の株式取得 （１）企業結合の概要 ① 被取得企業の名称及び事業の内容 被取得企業の名称 株式会社フジ土木設計 事業の内容 建設コンサルタント業、測量業 ② 企業結合を行った主な理由 株式会社フジ土木設計は1980年に有限会社フジ土木設計として設立（1991年に株式会社フジ土木設計に改組）され、測量・設計・補償・土木インフラ調査等を幅広く手掛け、調査段階から維持管理まで一貫したマネジメントサービスを提供し、北海道を中心に地域の安全安心を支え、地域と共に歩んできております。",
    "stockPrice": null,
    "netSales": 10347883000.0,
    "employees": 589,
    "operatingIncome": 146669000.0,
    "operatingIncomeRate": 1.4173817001989684,
    "depreciation": 150182000.0,
    "ebitda": 296851000.0,
    "ebitdaMargin": 2.8687123733424507,
    "marketCapitalization": null,
    "per": 14.0,
    "ev": null,
    "evPerEbitda": null,
    "pbr": null,
    "bps": 1290.88,
    "equity": 2020142000.0,
    "debt": 2776446000.0,
    "outstandingShares": 1563600,
    "netIncome": -87891000.0,
    "eps": -56.19,
    "cash": 1351071000.0,
    "retrievedDate": "2025-06-29"
  },
  {
    "secCode": "7409",
    "filerName": "ＡｅｒｏＥｄｇｅ株式会社",
    "docID": "S100UGK8",
    "docPdfURL": "https://disclosure2dl.edinet-fsa.go.jp/searchdocument/pdf/S100UGK8.pdf",
    "yahooURL": "https://finance.yahoo.co.jp/quote/7409.T",
    "periodEnd": "2024年6月期",
    "characteristic": "３ 【事業の内容】当社は、「ゼロからイチを創る ～常識を疑い、組織力で難しい課題に挑戦する～」という経営理念のもと、ものづくり企業として、航空機エンジン部品、並びにその他製品の加工製造・販売を主な事業内容としております。",
    "stockPrice": null,
    "netSales": null,
    "employees": null,
    "operatingIncome": null,
    "operatingIncomeRate": null,
    "depreciation": null,
    "ebitda": null,
    "ebitdaMargin": null,
    "marketCapitalization": null,
    "per": 0.2568,
    "ev": null,
    "evPerEbitda": null,
    "pbr": null,
    "bps": null,
    "equity": null,
    "debt": null,
    "outstandingShares": 3824700,
    "netIncome": null,
    "eps": null,
    "cash": null,
    "retrievedDate": "2025-06-29"
  },
  {
    "secCode": "3986",
    "filerName": "株式会社ビーブレイクシステムズ",
    "docID": "S100UG6X",
    "docPdfURL": "https://disclosure2dl.edinet-fsa.go.jp/searchdocument/pdf/S100UG6X.pdf",
    "yahooURL": "https://finance.yahoo.co.jp/quote/3986.T",
    "periodEnd": "2024年6月期",
    "characteristic": "３【事業の内容】 当社は、「世界が認めるシステム構築の仕組を世に広め、社会の発展に貢献する」という理念のもと、ドイツのＥＲＰベンダーであるＳＡＰ社の日本法人のシステムコンサルタントであった２名を中心に起業し、現在は、主にクラウドＥＲＰ（注１）の開発および販売を行うパッケージ事業と、主に顧客が構築するシステムの受託開発やＩＴ人材の派遣を行うシステムインテグレーション事業を行っております。",
    "stockPrice": null,
    "netSales": null,
    "employees": null,
    "operatingIncome": null,
    "operatingIncomeRate": null,
    "depreciation": null,
    "ebitda": null,
    "ebitdaMargin": null,
    "marketCapitalization": null,
    "per": 0.002,
    "ev": null,
    "evPerEbitda": null,
    "pbr": null,
    "bps": null,
    "equity": null,
    "debt": null,
    "outstandingShares": 1521000,
    "netIncome": null,
    "eps": null,
    "cash": null,
    "retrievedDate": "2025-06-29"
  },
  {
    "secCode": "246A",
    "filerName": "株式会社アスア",
    "docID": "S100UGL5",
    "docPdfURL": "https://disclosure2dl.edinet-fsa.go.jp/searchdocument/pdf/S100UGL5.pdf",
    "yahooURL": "https://finance.yahoo.co.jp/quote/246A.T",
    "periodEnd": "2024年6月期",
    "characteristic": "３【事業の内容】 当社は、「コンサルティング」×「クラウドサービス」で物流業界を人とデジタルの力で改善する」をミッションとし、物流事業者のドライバーの本音を引出し、安全対策への動機づけを行っております。",
    "stockPrice": null,
    "netSales": null,
    "employees": null,
    "operatingIncome": null,
    "operatingIncomeRate": null,
    "depreciation": null,
    "ebitda": null,
    "ebitdaMargin": null,
    "marketCapitalization": null,
    "per": 0.005,
    "ev": null,
    "evPerEbitda": null,
    "pbr": null,
    "bps": null,
    "equity": null,
    "debt": null,
    "outstandingShares": 2075000,
    "netIncome": null,
    "eps": null,
    "cash": null,
    "retrievedDate": "2025-06-29"
  },
  {
    "secCode": "9273",
    "filerName": "コーア商事ホールディングス株式会社",
    "docID": "S100UGDV",
    "docPdfURL": "https://disclosure2dl.edinet-fsa.go.jp/searchdocument/pdf/S100UGDV.pdf",
    "yahooURL": "https://finance.yahoo.co.jp/quote/9273.T",
    "periodEnd": "2024年6月期",
    "characteristic": "３【事業の内容】 (1）当社グループの事業の内容について 当社グループは、当社と子会社３社（連結子会社３社：コーア商事株式会社、コーアイセイ株式会社、コーアバイオテックベイ株式会社）で構成されており、原薬の仕入販売、製剤（医療用医薬品・一般用医薬品）の製造販売及び仕入販売、製剤に係る受託製造を主な事業としております。",
    "stockPrice": 701.3644,
    "netSales": 22134145000.0,
    "employees": 289,
    "operatingIncome": 4382313000.0,
    "operatingIncomeRate": 19.79888086935366,
    "depreciation": 726051000.0,
    "ebitda": 5108364000.0,
    "ebitdaMargin": 23.079111481378657,
    "marketCapitalization": 29526599602.72,
    "per": 9.46,
    "ev": 17922610602.72,
    "evPerEbitda": 3.5084834602076125,
    "pbr": 1.1791798786126197,
    "bps": 594.79,
    "equity": 25051674000.0,
    "debt": 1591384000.0,
    "outstandingShares": 42098800,
    "netIncome": 2946337000.0,
    "eps": 74.14,
    "cash": 13195373000.0,
    "retrievedDate": "2025-06-29"
  },
  {
    "secCode": "9340",
    "filerName": "株式会社アソインターナショナル",
    "docID": "S100UGG9",
    "docPdfURL": "https://disclosure2dl.edinet-fsa.go.jp/searchdocument/pdf/S100UGG9.pdf",
    "yahooURL": "https://finance.yahoo.co.jp/quote/9340.T",
    "periodEnd": "2024年6月期",
    "characteristic": "３【事業の内容】 当社グループは、当社及び連結子会社４社の計５社により構成されており、当社設立以来『Professionalな最新技術を世界から日本へ、日本から世界へ』という企業理念のもと、矯正歯科治療が必要な方々に歯科技工所（注１）としてオーダーメイドの歯科技工物（注２）を中心とした製品を提供しております。",
    "stockPrice": 1091.1599999999999,
    "netSales": 3544750000.0,
    "employees": 276,
    "operatingIncome": 545318000.0,
    "operatingIncomeRate": 15.38382114394527,
    "depreciation": 46575000.0,
    "ebitda": 591893000.0,
    "ebitdaMargin": 16.697736088581706,
    "marketCapitalization": 5327479583.999999,
    "per": 14.0,
    "ev": 3428667583.999999,
    "evPerEbitda": 5.792715210350518,
    "pbr": 1.9287986990030401,
    "bps": 565.72,
    "equity": 2763156000.0,
    "debt": 1181000.0,
    "outstandingShares": 4882400,
    "netIncome": 386406000.0,
    "eps": 77.94,
    "cash": 1899993000.0,
    "retrievedDate": "2025-06-29"
  },
  {
    "secCode": "3082",
    "filerName": "株式会社きちりホールディングス",
    "docID": "S100UGLS",
    "docPdfURL": "https://disclosure2dl.edinet-fsa.go.jp/searchdocument/pdf/S100UGLS.pdf",
    "yahooURL": "https://finance.yahoo.co.jp/quote/3082.T",
    "periodEnd": "2024年6月期",
    "characteristic": "３【事業の内容】 当社グループは、当社及び連結子会社５社により構成されており、飲食店の経営及びこれに付随する業務を主たる業務としております。",
    "stockPrice": 873.3516000000001,
    "netSales": 13747050000.0,
    "employees": 504,
    "operatingIncome": 784946000.0,
    "operatingIncomeRate": 5.709923219890813,
    "depreciation": 316097000.0,
    "ebitda": 1101043000.0,
    "ebitdaMargin": 8.009303814272881,
    "marketCapitalization": 9888261485.52,
    "per": 36.42,
    "ev": 7004764485.52,
    "evPerEbitda": 6.361935442593977,
    "pbr": 5.62364198325821,
    "bps": 155.3,
    "equity": 1839796000.0,
    "debt": 100000000.0,
    "outstandingShares": 11322200,
    "netIncome": 256555000.0,
    "eps": 23.98,
    "cash": 2983497000.0,
    "retrievedDate": "2025-06-29"
  },
  {
    "secCode": "3632",
    "filerName": "グリー株式会社",
    "docID": "S100UFY3",
    "docPdfURL": "https://disclosure2dl.edinet-fsa.go.jp/searchdocument/pdf/S100UFY3.pdf",
    "yahooURL": "https://finance.yahoo.co.jp/quote/3632.T",
    "periodEnd": "2024年6月期",
    "characteristic": "（セグメント情報等） 【セグメント情報】 １．報告セグメントの概要 当社の報告セグメントは、当社の構成単位のうち分離された財務情報が入手可能であり、取締役会が、経営資源の配分の決定及び業績を評価するために、定期的に検討を行う対象となっているものであります。",
    "stockPrice": 526.9593,
    "netSales": 61309000000.0,
    "employees": 1580,
    "operatingIncome": 5981000000.0,
    "operatingIncomeRate": 9.755500823696357,
    "depreciation": 343000000.0,
    "ebitda": 6324000000.0,
    "ebitdaMargin": 10.314961914237713,
    "marketCapitalization": 94463988820.31999,
    "per": 19.67,
    "ev": 33875988820.319992,
    "evPerEbitda": 5.356734475066412,
    "pbr": 0.9492538684632428,
    "bps": 555.13,
    "equity": 95530000000.0,
    "debt": 16700000000.0,
    "outstandingShares": 179262400,
    "netIncome": 4630000000.0,
    "eps": 26.79,
    "cash": 77288000000.0,
    "retrievedDate": "2025-06-29"
  },
  {
    "secCode": "9162",
    "filerName": "株式会社ブリーチ",
    "docID": "S100UGJ2",
    "docPdfURL": "https://disclosure2dl.edinet-fsa.go.jp/searchdocument/pdf/S100UGJ2.pdf",
    "yahooURL": "https://finance.yahoo.co.jp/quote/9162.T",
    "periodEnd": "2024年6月期",
    "characteristic": "３【事業等のリスク】 本書に記載した当社の事業の状況、経理の状況等に関する事項のうち、投資者の判断に重要な影響を及ぼす可能性のある事項には、以下のようなものがあります。",
    "stockPrice": null,
    "netSales": null,
    "employees": null,
    "operatingIncome": null,
    "operatingIncomeRate": null,
    "depreciation": null,
    "ebitda": null,
    "ebitdaMargin": null,
    "marketCapitalization": null,
    "per": 0.003,
    "ev": null,
    "evPerEbitda": null,
    "pbr": null,
    "bps": null,
    "equity": null,
    "debt": null,
    "outstandingShares": 25476800,
    "netIncome": null,
    "eps": null,
    "cash": null,
    "retrievedDate": "2025-06-29"
  },
  {
    "secCode": "3628",
    "filerName": "株式会社データホライゾン",
    "docID": "S100UGCZ",
    "docPdfURL": "https://disclosure2dl.edinet-fsa.go.jp/searchdocument/pdf/S100UGCZ.pdf",
    "yahooURL": "https://finance.yahoo.co.jp/quote/3628.T",
    "periodEnd": "2024年6月期",
    "characteristic": "３【事業の内容】 当社グループの事業の目的は、我が国で少子高齢化が進み医療費の増加が大きな社会問題となるなか、国民の健康と医療費適正化に貢献し続けることであり、当社グループは、当社および連結子会社３社で構成されております。",
    "stockPrice": null,
    "netSales": 5007033000.0,
    "employees": 374,
    "operatingIncome": -789849000.0,
    "operatingIncomeRate": -15.774791178728002,
    "depreciation": 388103000.0,
    "ebitda": -401746000.0,
    "ebitdaMargin": -8.02363395647682,
    "marketCapitalization": null,
    "per": 20.0,
    "ev": null,
    "evPerEbitda": null,
    "pbr": null,
    "bps": 245.38,
    "equity": 3216305000.0,
    "debt": 1980000000.0,
    "outstandingShares": 12673600,
    "netIncome": -807185000.0,
    "eps": -63.7,
    "cash": 1424737000.0,
    "retrievedDate": "2025-06-29"
  },
  {
    "secCode": "8945",
    "filerName": "サンネクスタグループ株式会社",
    "docID": "S100UG7Y",
    "docPdfURL": "https://disclosure2dl.edinet-fsa.go.jp/searchdocument/pdf/S100UG7Y.pdf",
    "yahooURL": "https://finance.yahoo.co.jp/quote/8945.T",
    "periodEnd": "2024年6月期",
    "characteristic": "（保有目的）当社が展開するサービスにおいて補完関係を持ち、今後のサービス拡充においても協業関係の維持を目的として継続保有しております。",
    "stockPrice": 979.4720000000001,
    "netSales": 8371365000.0,
    "employees": 643,
    "operatingIncome": 653569000.0,
    "operatingIncomeRate": 7.807197511994758,
    "depreciation": 78381000.0,
    "ebitda": 731950000.0,
    "ebitdaMargin": 8.743496430988255,
    "marketCapitalization": 10546170918.400002,
    "per": 5.2,
    "ev": 3230099918.4000015,
    "evPerEbitda": 4.413006241409934,
    "pbr": 1.1576041223467122,
    "bps": 846.12,
    "equity": 7908182000.0,
    "debt": 383000.0,
    "outstandingShares": 10767200,
    "netIncome": 1775416000.0,
    "eps": 188.36,
    "cash": 7316454000.0,
    "retrievedDate": "2025-06-29"
  },
  {
    "secCode": "7707",
    "filerName": "プレシジョン・システム・サイエンス株式会社",
    "docID": "S100UGNR",
    "docPdfURL": "https://disclosure2dl.edinet-fsa.go.jp/searchdocument/pdf/S100UGNR.pdf",
    "yahooURL": "https://finance.yahoo.co.jp/quote/7707.T",
    "periodEnd": "2024年6月期",
    "characteristic": "３ 【事業の内容】当社グループ(当社及び当社の関係会社)は、当社及び子会社４社、持分法適用共同支配企業１社で構成されており、主としてバイオ関連業界において、ラボ(研究室)自動化や臨床検査用の各種装置、それらに使用される試薬や反応容器などの消耗品類の開発及び製造販売を行っております。",
    "stockPrice": null,
    "netSales": 3979954000.0,
    "employees": 158,
    "operatingIncome": -956246000.0,
    "operatingIncomeRate": -24.026559100934332,
    "depreciation": 409081000.0,
    "ebitda": -547165000.0,
    "ebitdaMargin": -13.748023218358805,
    "marketCapitalization": null,
    "per": 149.93,
    "ev": null,
    "evPerEbitda": null,
    "pbr": null,
    "bps": 149.93,
    "equity": 4142850000.0,
    "debt": 289673000.0,
    "outstandingShares": 27623700,
    "netIncome": -1121480000.0,
    "eps": -40.59,
    "cash": 1895220000.0,
    "retrievedDate": "2025-06-29"
  }
]